{
  "users": [],
  "vinhos": [
    {
      "id": 1,
      "nome": "La Pepica Monastrell Valencia D.O. 2017",
      "img": "https://res.cloudinary.com/evino/image/upload/q_auto:good,fl_progressive:steep,f_auto,dpr_1.0,h_434/v1/products/1000003971-standing-front.png",
      "categoria": "Vinho Tinto",
      "pais": "Espanha",
      "volume": "750ml",
      "teor": 13.5,
      "safra": 2017,
      "preco": 30
    },
    {
      "id": 2,
      "nome": "Tittarelli Desde 1915 Malbec Vino Tinto 2020",
      "img": "https://res.cloudinary.com/evino/image/upload/q_auto:good,fl_progressive:steep,f_auto,dpr_1.0,h_434/v1/products/1000003931-standing-front.png",
      "categoria": "Vinho Tinto",
      "pais": "Argentina",
      "volume": "750ml",
      "teor": 13,
      "safra": 2020,
      "preco": 35
    },
    {
      "id": 3,
      "nome": "Fauna Winemaker Selection Red Blend",
      "img": "https://res.cloudinary.com/evino/image/upload/q_auto:good,fl_progressive:steep,f_auto,dpr_1.0,h_434/v1/products/1000003557-standing-front.png",
      "categoria": "Vinho Tinto",
      "pais": "Chile",
      "volume": "750ml",
      "teor": 12,
      "safra": 2022,
      "preco": 40
    },
    {
      "id": 4,
      "nome": "Condor Peak Sweet Red Wine Suave 2020",
      "img": "https://res.cloudinary.com/evino/image/upload/q_auto:good,fl_progressive:steep,f_auto,dpr_1.0,h_434/v1/products/1000004895-standing-front.png",
      "categoria": "Vinho Tinto",
      "pais": "Argentina",
      "volume": "750ml",
      "teor": 12,
      "safra": 2022,
      "preco": 27
    },
    {
      "id": 5,
      "nome": "Villa Puccini Brunello di Montalcino DOCG 2015",
      "img": "https://res.cloudinary.com/evino/image/upload/q_auto:good,fl_progressive:steep,f_auto,dpr_1.0,h_434/v1/products/1000003273-standing-front.png",
      "categoria": "Vinho Tinto",
      "pais": "Italia",
      "volume": "750ml",
      "teor": 14,
      "safra": 2015,
      "preco": 470
    },
    {
      "id": 6,
      "nome": "Gran Anciano Oak Matured Tempranillo Valdepeñas DOP 2019",
      "img": "https://res.cloudinary.com/evino/image/upload/q_auto:good,fl_progressive:steep,f_auto,dpr_1.0,h_434/v1/products/1000004942-standing-front.png",
      "categoria": "Vinho Tinto",
      "pais": "Espanha",
      "volume": "750ml",
      "teor": 14,
      "safra": 2015,
      "preco": 90
    },
    {
      "id": 7,
      "nome": "Santa Cristina Amabile Casasole Classico Orvieto DOC 2019",
      "img": "https://res.cloudinary.com/evino/image/upload/q_auto:good,fl_progressive:steep,f_auto,dpr_1.0,h_434/v1/products/1000002816-standing-front.png",
      "categoria": "Vinho Branco",
      "pais": "Italia",
      "volume": "750ml",
      "teor": 14,
      "safra": 2018,
      "preco": 150
    },
    {
      "id": 8,
      "nome": "Villa Matilde Cecubo 2014",
      "img": "https://res.cloudinary.com/evino/image/upload/q_auto:good,fl_progressive:steep,f_auto,dpr_1.0,h_434/v1/products/1000002052-standing-front.png",
      "categoria": "Vinho Tinto",
      "pais": "Italia",
      "volume": "750ml",
      "teor": 13,
      "safra": 2014,
      "preco": 299
    },
    {
      "id": 9,
      "nome": "Anciano Malbec-Viognier 2020",
      "img": "https://res.cloudinary.com/evino/image/upload/q_auto:good,fl_progressive:steep,f_auto,dpr_1.0,h_434/v1/products/1000004538-standing-front.png",
      "categoria": "Vinho Tinto",
      "pais": "Argentina",
      "volume": "750ml",
      "teor": 11,
      "safra": 2015,
      "preco": 109
    },
    {
      "id": 10,
      "nome": "Anciano Old Magnum Reserva 7 years Valdepeñas DOP 2011",
      "img": "https://res.cloudinary.com/evino/image/upload/q_auto:good,fl_progressive:steep,f_auto,dpr_1.0,h_434/v1/products/1000000840-standing-front.png",
      "categoria": "Vinho Tinto",
      "pais": "Espanha",
      "volume": "750ml",
      "teor": 11,
      "safra": 2015,
      "preco": 140
    }
  ]
}
